{
 "links": {
  "self": "/adapter-calypso/v3/query/node/68f09a34-d984-11eb-be76-ab3074eb89d3"
 },
 "id": "68f09a34-d984-11eb-be76-ab3074eb89d3",
 "type": "ASSET/PROGRAMME",
 "childTypes": {
  "images": {
   "nodeTypes": [
    "CMS/IMAGE/MASTER"
   ],
   "count": 10
  },
  "shortforms": {
   "nodeTypes": [
    "ASSET/SHORTFORM/THEATRICAL"
   ],
   "count": 1
  },
  "trailers": {
   "nodeTypes": [
    "ASSET/SHORTFORM/THEATRICAL"
   ],
   "count": 1
  }
 },
 "attributes": {
  "alternativeDate": [
   {
    "type": "released",
    "value": "2010-07-16",
    "dateType": "theatrical",
    "territory": "US"
   }
  ],
  "audioDescribed": false,
  "badging": {
   "videoFormats": [
    {
     "videoFormat": "HD",
     "colourSpaces": [
      "SDR"
     ]
    }
   ],
   "audioTracks": [
    "Stereo"
   ]
  },
  "cast": [
   "Leonardo DiCaprio",
   "Ken Watanabe",
   "Joseph Gordon-Levitt",
   "Marion Cotillard",
   "Elliot Page",
   "Tom Hardy",
   "Cillian Murphy",
   "Tom Berenger",
   "Michael Caine"
  ],
  "channel": {
   "accessChannel": "5470883989996030105",
   "name": "Warner Bros"
  },
  "childNodeTypes": [
   "ASSET/SHORTFORM/THEATRICAL",
   "CMS/IMAGE/MASTER"
  ],
  "classification": [
   "MOVIES"
  ],
  "closedCaptioned": true,
  "contentSegments": [
   "D2C"
  ],
  "createdDate": 1625044828442,
  "deviceAvailabilities": [
   {
    "format": "HD",
    "mediaType": "ARCHIVE",
    "offerStage": "NOTAPPLICABLE",
    "offerStartTs": 1706781600000,
    "offerEndTs": 1709287140000,
    "streamable": true,
    "downloadable": true,
    "contentSegment": "D2C",
    "videoFormat": "HD",
    "videoFormatVariant": "SDR",
    "colourSpace": "SDR"
   }
  ],
  "deviceAvailability": {
   "available": true
  },
  "director": [
   "Christopher Nolan"
  ],
  "durationMilliseconds": 8889000,
  "durationMinutes": 148,
  "durationSeconds": 8889,
  "editorialWarningText": "",
  "fanCriticRating": [
   {
    "source": "RT",
    "fanScore": 91,
    "criticScore": 87,
    "tags": [
     "FRESH"
    ]
   }
  ],
  "formats": {
   "HD": {
    "audioTracks": {
     "spa": [
      "Stereo"
     ],
     "eng": [
      "Stereo"
     ]
    },
    "eventStage": "NOTAPPLICABLE",
    "contentId": "GMO_00000000355710_01",
    "availability": {
     "available": true,
     "mediaType": "ARCHIVE",
     "offerStage": "NOTAPPLICABLE",
     "offerStartTs": 1706781600000,
     "offerEndTs": 1709287140000,
     "streamable": true,
     "downloadable": true,
     "availableDevices": [
      {
       "type": "COMPUTER",
       "platform": "MAC"
      },
      {
       "type": "COMPUTER",
       "platform": "PC"
      },
      {
       "type": "CONSOLE",
       "platform": "PLAYSTATION"
      },
      {
       "type": "CONSOLE",
       "platform": "XBOX"
      },
      {
       "type": "IPSETTOPBOX",
       "platform": "APPLETV"
      },
      {
       "type": "IPSETTOPBOX",
       "platform": "CHROMECAST"
      },
      {
       "type": "IPSETTOPBOX",
       "platform": "FIRETV"
      },
      {
       "type": "IPSETTOPBOX",
       "platform": "RDK"
      },
      {
       "type": "IPSETTOPBOX",
       "platform": "XFINITY-FLEX"
      },
      {
       "type": "IPSETTOPBOX",
       "platform": "XFINITY-X1"
      },
      {
       "type": "IPSTB",
       "platform": "ROKU"
      },
      {
       "type": "MOBILE",
       "platform": "ANDROID"
      },
      {
       "type": "MOBILE",
       "platform": "IOS"
      },
      {
       "type": "SETTOPBOX",
       "platform": "ROKU"
      },
      {
       "type": "TABLET",
       "platform": "ANDROID"
      },
      {
       "type": "TABLET",
       "platform": "IOS"
      },
      {
       "type": "TV",
       "platform": "ANDROIDTV"
      },
      {
       "type": "TV",
       "platform": "HISENSE-VIDAA"
      },
      {
       "type": "TV",
       "platform": "LG"
      },
      {
       "type": "TV",
       "platform": "SAMSUNG"
      },
      {
       "type": "TV",
       "platform": "VIZIO"
      }
     ],
     "extendedOfferStartTs": 1706781600000,
     "extendedOfferEndTs": 1709287140000,
     "contentSegment": "D2C",
     "videoFormat": "HD",
     "videoFormatVariant": "SDR",
     "colourSpace": "SDR"
    },
    "startOfCredits": 8460661,
    "markers": {
     "SOCR": 8460661
    }
   }
  },
  "genreList": [
   {
    "subgenre": [
     "Action"
    ],
    "genre": [
     "Movies"
    ]
   },
   {
    "subgenre": [
     "Sci-Fi"
    ],
    "genre": [
     "Movies"
    ]
   },
   {
    "subgenre": [
     "Adventure"
    ],
    "genre": [
     "Movies"
    ]
   },
   {
    "subgenre": [
     "Thriller"
    ],
    "genre": [
     "Movies"
    ]
   }
  ],
  "genres": [
   "Action",
   "Sci-Fi",
   "Adventure",
   "Thriller"
  ],
  "gracenoteId": "MV002624410000",
  "images": [
   {
    "url": "https://imageservice.disco.peacocktv.com/uuid/976dde50-17a6-3034-98a7-5b5a34779fb3/LAND_16_9?language=eng&territory=US&proposition=NBCUOTT&version=444eb61a-3564-3d3f-97ad-c52bd094f2ef",
    "type": "landscape"
   },
   {
    "url": "",
    "type": "portrait"
   },
   {
    "url": "",
    "type": "midsize"
   },
   {
    "url": "https://imageservice.disco.peacocktv.com/uuid/976dde50-17a6-3034-98a7-5b5a34779fb3/SCENE_16_9?language=eng&territory=US&proposition=NBCUOTT&version=444eb61a-3564-3d3f-97ad-c52bd094f2ef",
    "type": "scene169"
   },
   {
    "url": "https://imageservice.disco.peacocktv.com/uuid/976dde50-17a6-3034-98a7-5b5a34779fb3/TITLE_ART_16_9?language=eng&territory=US&proposition=NBCUOTT&version=51f404d1-85f4-3df6-b4ab-cc52ebfd8edf",
    "type": "titleArt169"
   },
   {
    "url": "https://imageservice.disco.peacocktv.com/uuid/976dde50-17a6-3034-98a7-5b5a34779fb3/KEY_ART_3_4?language=eng&territory=US&proposition=NBCUOTT&version=f327e222-4f07-321e-85f4-29e68abc70e8",
    "type": "nonTitleArt34"
   },
   {
    "url": "https://imageservice.disco.peacocktv.com/uuid/976dde50-17a6-3034-98a7-5b5a34779fb3/SCENE_3_4?language=eng&territory=US&version=2d2d5476-cfb0-392f-802a-c08fd7cb2a48",
    "type": "scene34"
   },
   {
    "url": "https://imageservice.disco.peacocktv.com/uuid/976dde50-17a6-3034-98a7-5b5a34779fb3/KEY_ART_16_9?language=eng&territory=US&proposition=NBCUOTT&version=d13ec77b-421a-3764-886f-c13c7bd9ba31",
    "type": "nonTitleArt169"
   },
   {
    "url": "https://imageservice.disco.peacocktv.com/uuid/976dde50-17a6-3034-98a7-5b5a34779fb3/TITLE_ART_3_4?language=eng&territory=US&version=2f757228-9e85-36db-af49-86a86a6147bf",
    "type": "titleArt34"
   },
   {
    "url": "https://imageservice.disco.peacocktv.com/uuid/976dde50-17a6-3034-98a7-5b5a34779fb3/TITLE_TREATMENT?language=eng&territory=US&proposition=NBCUOTT&version=48157c13-fd4a-3feb-922c-636b71b982ff",
    "type": "titleLogo"
   }
  ],
  "merlinId": "8368357466401273112",
  "ottCertificate": "PG13",
  "producer": [
   "Christopher Nolan",
   "Emma Thomas",
   "Chris Brigham",
   "Thomas Tull"
  ],
  "programmeUuid": "976dde50-17a6-3034-98a7-5b5a34779fb3",
  "providerId": "5470883989996030105",
  "providerVariantId": "e686fee9-a575-3773-a188-2c1e7c6025ac",
  "rating": "4.5",
  "ratingPercentage": 87,
  "runtime": "02:28:09",
  "sectionNavigation": "ENTERTAINMENT",
  "slug": "/movies/adventure/inception/e686fee9-a575-3773-a188-2c1e7c6025ac",
  "sortTitle": "inception",
  "subtitled": false,
  "synopsis": "A thief who enters people's dreams and steals their secrets must plant an idea in a man's mind.",
  "synopsisBrief": "A thief who enters people's dreams and steals their secrets must plant an idea in a man's mind.",
  "synopsisLong": "A thief who enters people's dreams and steals their secrets gets a shot at redemption when he is given the dangerous task of planting an idea in someone's subconscious.",
  "synopsisShort": "A thief who enters people's dreams and steals their secrets must plant an idea in a man's mind.",
  "targetAudience": {
   "id": "PG13"
  },
  "title": "Inception",
  "titleLong": "Inception",
  "titleMedium": "Inception",
  "uriid": "uriId",
  "year": 2010
 }
}
